netcontrold/__init__.py
netcontrold/app/__init__.py
netcontrold/app/ncd.py
netcontrold/doc/index.rst
netcontrold/doc/faq/faq_general.rst
netcontrold/doc/intro/ncd_overview.rst
netcontrold/lib/__init__.py
netcontrold/lib/config.py
netcontrold/lib/dataif.py
netcontrold/lib/error.py
netcontrold/lib/util.py
netcontrold/tests/lib/test_data_coll.py
netcontrold/tests/lib/test_pmd_load_variance.py
netcontrold/tests/lib/test_pmd_rebal.py
netcontrold/tests/lib/test_prelim.py
netcontrold/tests/lib/test_util.py
netcontrold-1.0.17.data/scripts/ncd_cb_pktdrop
netcontrold-1.0.17.data/scripts/ncd_ctl
netcontrold-1.0.17.data/scripts/ncd_watch
usr/lib/systemd/system/netcontrold.service
netcontrold-1.0.17.dist-info/AUTHORS
netcontrold-1.0.17.dist-info/COPYING
netcontrold-1.0.17.dist-info/LICENSE
netcontrold-1.0.17.dist-info/METADATA
netcontrold-1.0.17.dist-info/WHEEL
netcontrold-1.0.17.dist-info/top_level.txt
netcontrold-1.0.17.dist-info/RECORD
