Metadata-Version: 2.1
Name: netcontrold
Version: 1.0.17
Summary: Network control daemon for Open_vSwitch 
Home-page: https://github.com/netcontrold/netcontrold-py.git
Author: Gowrishankar Muthukrishnan
Author-email: gmuthukr@redhat.com
License: Apache
Platform: UNKNOWN
Classifier: Development Status :: 4 - Beta
Classifier: Environment :: Console
Classifier: License :: OSI Approved :: Apache Software License
Classifier: Programming Language :: Python :: 2
Classifier: Programming Language :: Python :: 3
Classifier: Topic :: System :: Monitoring
Requires-Python: >=3
